{
  "metainfo" : {
    "type" : "Databricks",
    "fabricId" : "1174",
    "jobId" : "jobs/example_job_observability",
    "name" : "example_job_observability",
    "schedule" : "0 0 0 1/1 * ? *",
    "scheduleTimeZone" : "UTC",
    "jobClusterMode" : {
      "clusterMode" : "Single"
    },
    "enabled" : false,
    "defaultClusterSize" : "small",
    "alerting" : {
      "emails" : "",
      "onStart" : false,
      "onSuccess" : false,
      "onFailure" : false
    },
    "maxConcurrentRuns" : 1,
    "processDefaultSettings" : {
      "type" : "Inherited",
      "retries" : 0,
      "alerting" : {
        "emails" : "",
        "onStart" : false,
        "onSuccess" : false,
        "onFailure" : false
      }
    },
    "availableFabrics" : [ {
      "id" : "1673",
      "name" : "test1",
      "clusterSizes" : {
        "default" : "Small",
        "availableClusterSizes" : [ "Small" ]
      },
      "pylibsResolutionMode" : {
        "PublicCentral" : { }
      },
      "scalalibsResolutionMode" : {
        "PublicCentral" : { }
      }
    }, {
      "id" : "1691",
      "name" : "dev",
      "clusterSizes" : {
        "default" : "small",
        "availableClusterSizes" : [ "small" ]
      },
      "pylibsResolutionMode" : {
        "PublicCentral" : { }
      },
      "scalalibsResolutionMode" : {
        "PublicCentral" : { }
      }
    }, {
      "id" : "1744",
      "name" : "default-rj-dev",
      "clusterSizes" : {
        "default" : "small",
        "availableClusterSizes" : [ "small", "large", "medium" ]
      },
      "pylibsResolutionMode" : {
        "PublicCentral" : { }
      },
      "scalalibsResolutionMode" : {
        "PublicCentral" : { }
      }
    }, {
      "id" : "1684",
      "name" : "workday-default",
      "clusterSizes" : {
        "default" : "small",
        "availableClusterSizes" : [ "small", "medium", "large" ]
      },
      "pylibsResolutionMode" : {
        "PublicCentral" : { }
      },
      "scalalibsResolutionMode" : {
        "PublicCentral" : { }
      }
    }, {
      "id" : "2002",
      "name" : "test-catalog",
      "clusterSizes" : {
        "default" : "small",
        "availableClusterSizes" : [ "small" ]
      },
      "pylibsResolutionMode" : {
        "PublicCentral" : { }
      },
      "scalalibsResolutionMode" : {
        "PublicCentral" : { }
      }
    }, {
      "id" : "2055",
      "name" : "e2-unity-single-user",
      "clusterSizes" : {
        "default" : "small",
        "availableClusterSizes" : [ "small" ]
      },
      "pylibsResolutionMode" : {
        "PublicCentral" : { }
      },
      "scalalibsResolutionMode" : {
        "PublicCentral" : { }
      }
    }, {
      "id" : "1807",
      "name" : "PoC-PNC",
      "clusterSizes" : {
        "default" : "Small",
        "availableClusterSizes" : [ "Small" ]
      },
      "pylibsResolutionMode" : {
        "PublicCentral" : { }
      },
      "scalalibsResolutionMode" : {
        "PublicCentral" : { }
      }
    }, {
      "id" : "1840",
      "name" : "default-fabric",
      "clusterSizes" : {
        "default" : "small",
        "availableClusterSizes" : [ "small" ]
      },
      "pylibsResolutionMode" : {
        "PublicCentral" : { }
      },
      "scalalibsResolutionMode" : {
        "PublicCentral" : { }
      }
    }, {
      "id" : "1174",
      "name" : "demos",
      "clusterSizes" : {
        "default" : "small",
        "availableClusterSizes" : [ "small" ]
      },
      "pylibsResolutionMode" : {
        "PublicCentral" : { }
      },
      "scalalibsResolutionMode" : {
        "PublicCentral" : { }
      }
    }, {
      "id" : "1941",
      "name" : "jpmc-training",
      "clusterSizes" : {
        "default" : "Small",
        "availableClusterSizes" : [ "Small" ]
      },
      "pylibsResolutionMode" : {
        "PublicCentral" : { }
      },
      "scalalibsResolutionMode" : {
        "PublicCentral" : { }
      }
    } ]
  },
  "processes" : {
    "Xw3-FXXFWG1NhE_fvuT6L$$zH2LvzoD6yZ02vryEq4nr" : {
      "id" : "Xw3-FXXFWG1NhE_fvuT6L$$zH2LvzoD6yZ02vryEq4nr",
      "component" : "Pipeline",
      "metadata" : {
        "label" : "IngestData",
        "slug" : "IngestData",
        "x" : 693.5999755859375,
        "y" : 372
      },
      "ports" : {
        "inputs" : [ {
          "id" : "ODk2PTbPFChOTY2IP-o75$$kowXUO1Lfx5MOvdFXXnTc",
          "slug" : ""
        } ],
        "outputs" : [ {
          "id" : "jj9JNQep6Ct6KplCfOzh1$$pVv4oqxGCpRrm9q_q8nUi",
          "slug" : ""
        } ]
      },
      "settings" : {
        "type" : "Inherited",
        "alerting" : {
          "emails" : "",
          "onStart" : false,
          "onSuccess" : false,
          "onFailure" : false
        }
      },
      "properties" : {
        "pipelineId" : "pipelines/IngestData",
        "configurations" : {
          "schema" : [ {
            "name" : "env",
            "kind" : {
              "type" : "string",
              "value" : "unspecified"
            },
            "optional" : false,
            "isWorkflowNodeConfiguration" : false
          } ],
          "instances" : {
            "HelloCICD" : [ "default", "qa", "dev", "prod" ]
          },
          "overrides" : { },
          "selectedInstance" : "default"
        }
      }
    }
  },
  "connections" : [ ]
}